SSLProxies24/Check.py
SSLProxies24/Feed.py
SSLProxies24/__init__.py
SSLProxies24-1.3.6.dist-info/DESCRIPTION.rst
SSLProxies24-1.3.6.dist-info/METADATA
SSLProxies24-1.3.6.dist-info/RECORD
SSLProxies24-1.3.6.dist-info/WHEEL
SSLProxies24-1.3.6.dist-info/metadata.json
SSLProxies24-1.3.6.dist-info/top_level.txt
