Metadata-Version: 2.0
Name: SSLProxies24
Version: 1.3.6
Summary: Obtenha e valide vários Proxys diariamente com este pacote. (Thread).
Home-page: https://github.com/riquedev/SSLProxies24Feed
Author: Henrique da Silva Santos (rique_dev)
Author-email: rique_dev@hotmail.com
License: MIT
Download-URL: https://github.com/riquedev/SSLProxies24Feed/archive/master.zip
Keywords: proxy,ssl,24,feed,blog,anonymous
Platform: UNKNOWN
Requires: requests
Requires: defusedxml
Requires-Python: >=3.6
Requires-Dist: defusedxml
Requires-Dist: requests
